flatpy/__init__.py
flatpy/nD.py
flatpy/twoD.py
flatpy/utils.py
flatpy-0.0.4.dist-info/LICENSE
flatpy-0.0.4.dist-info/METADATA
flatpy-0.0.4.dist-info/WHEEL
flatpy-0.0.4.dist-info/top_level.txt
flatpy-0.0.4.dist-info/RECORD
