Metadata-Version: 2.1
Name: flatpy
Version: 0.0.4
Summary: A library for computing samplings in arbitrary dimensions
Author-email: Dan Maljovec <maljovec002@gmail.com>
Project-URL: Documentation, https://flatpy.readthedocs.io/en/latest/
Project-URL: Source, https://github.com/maljovec/flatpy
Classifier: Development Status :: 3 - Alpha
Classifier: Intended Audience :: Science/Research
Classifier: License :: OSI Approved :: BSD License
Classifier: Programming Language :: C++
Classifier: Programming Language :: Python :: 3
Classifier: Topic :: Scientific/Engineering :: Mathematics
Requires-Python: >=3.7
License-File: LICENSE
